.envrc
.gitignore
LICENSE
MANIFEST.in
README.md
dev-requirements.txt
setup.cfg
setup.py
snappy_stream.sublime-project
snappy_stream/__init__.py
snappy_stream/errors.py
snappy_stream/openers.py
snappy_stream/requirements.txt
snappy_stream.egg-info/PKG-INFO
snappy_stream.egg-info/SOURCES.txt
snappy_stream.egg-info/dependency_links.txt
snappy_stream.egg-info/not-zip-safe
snappy_stream.egg-info/requires.txt
snappy_stream.egg-info/top_level.txt
snappy_stream/detail/__init__.py
snappy_stream/detail/priv_bytes_opener.py
snappy_stream/io_wrapper/__init__.py
snappy_stream/io_wrapper/chunk_io_wrapper.py
snappy_stream/io_wrapper/snappy_io_wrapper.py
snappy_stream/test/__init__.py
snappy_stream/test/test_snappy_wrapper.py