Metadata-Version: 1.1
Name: snappy-stream
Version: 0.9.0
Summary: Streaming snappy compression for Python file-like objects, with helpers for local FS + S3
Home-page: https://github.com/CurataEng/snappy-stream
Author: Scott Ivey / Curata Inc.
Author-email: scott@curata.com
License: MIT
Platform: any
Classifier: Environment :: Web Environment
Classifier: Intended Audience :: Developers
Classifier: License :: OSI Approved :: MIT License
Classifier: Operating System :: OS Independent
Classifier: Programming Language :: Python :: 2
Classifier: Programming Language :: Python :: 3
Classifier: Topic :: Software Development :: Libraries :: Python Modules
